busytag/__init__.py
busytag/busytag_types.py
busytag/config.py
busytag/device.py
busytag/tool.py
busytag-0.1.5.dist-info/METADATA
busytag-0.1.5.dist-info/WHEEL
busytag-0.1.5.dist-info/entry_points.txt
busytag-0.1.5.dist-info/licenses/LICENSE
busytag-0.1.5.dist-info/RECORD
