Metadata-Version: 2.4
Name: busytag
Version: 0.1.5
Summary: A library and CLI tool to control Busy Tag devices.
Project-URL: Homepage, https://github.com/acoster/busytag_tool
Project-URL: Issues, https://github.com/acoster/busytag_tool/issues
Project-URL: Repository, https://github.com/acoster/busytag_tool.git
Author-email: Alex Coster <alex@coster.ch>
License-Expression: MIT
License-File: LICENSE
Classifier: Development Status :: 5 - Production/Stable
Classifier: Environment :: Console
Classifier: License :: OSI Approved :: MIT License
Classifier: Operating System :: OS Independent
Classifier: Topic :: System :: Hardware :: Universal Serial Bus (USB) :: Communications Device Class (CDC)
Requires-Python: >=3.11
Requires-Dist: absl-py~=2.3.0
Requires-Dist: progress~=1.6
Requires-Dist: pyserial~=3.5
Requires-Dist: pytest
Requires-Dist: tomlkit~=0.13.2
